Metadata-Version: 1.0
Name: rnapk
Version: 0.12
Summary: A simple utility to send React Native APKs via email.
Home-page: https://github.com/srishanbhattarai/rnapk
Author: Srishan Bhattarai
Author-email: srishanbhattarai@gmail.com
License: MIT
Platform: UNKNOWN
